cgiw/__init__.py
cgiw/composers.py
cgiw/decorators.py
cgiw/exceptions.py
cgiw/handler.py
cgiw/logger.py
cgiw/parsers.py
cgiw/responses.py
cgiw/run.py
cgiw/types.py
cgiw-1.0.5.dist-info/LICENSE
cgiw-1.0.5.dist-info/METADATA
cgiw-1.0.5.dist-info/WHEEL
cgiw-1.0.5.dist-info/top_level.txt
cgiw-1.0.5.dist-info/RECORD
