Metadata-Version: 2.1
Name: cgiw
Version: 1.0.5
Summary: A framework for building python cgi scripts
Author-email: James Rao <jamesnarayanrao@gmail.com>
Project-URL: Homepage, https://github.com/JamesRao98/cgiw
Project-URL: Bug Tracker, https://github.com/JamesRao98/cgiw/issues
Classifier: Programming Language :: Python :: 3
Classifier: License :: OSI Approved :: MIT License
Classifier: Operating System :: OS Independent
Requires-Python: >=3.7
License-File: LICENSE
